pyautomlib/__init__.py
pyautomlib/classification.py
pyautomlib/clustering.py
pyautomlib/config.py
pyautomlib/preprocess.py
pyautomlib/regression.py
pyautomlib-0.0.5.dist-info/LICENSE
pyautomlib-0.0.5.dist-info/METADATA
pyautomlib-0.0.5.dist-info/WHEEL
pyautomlib-0.0.5.dist-info/top_level.txt
pyautomlib-0.0.5.dist-info/RECORD
