Metadata-Version: 2.1
Name: pyautomlib
Version: 0.0.5
Summary: Creating machine learning and preprocessing models
Author: nubufi (Numan Burak Fidan)
Author-email: <numanburakfidan@yandex.com>
Keywords: python,machine learning,clustering,regression,data processing,classification
Classifier: Development Status :: 1 - Planning
Classifier: Intended Audience :: Developers
Classifier: Programming Language :: Python :: 3
Classifier: Operating System :: Unix
Classifier: Operating System :: MacOS :: MacOS X
Classifier: Operating System :: Microsoft :: Windows
License-File: LICENSE
Requires-Dist: numpy
Requires-Dist: pandas
Requires-Dist: sklearn
Requires-Dist: joblib
Requires-Dist: xgboost
Requires-Dist: lightgbm
